ZhihuWendaRuheKandai42SuiZhongxingWangxinYanfaFuzerenOuJianxinBeiCituiHouZhuiwang/README.md
ZhihuWendaRuheKandai42SuiZhongxingWangxinYanfaFuzerenOuJianxinBeiCituiHouZhuiwang/__init__.py
ZhihuWendaRuheKandai42SuiZhongxingWangxinYanfaFuzerenOuJianxinBeiCituiHouZhuiwang/__main__.py
ZhihuWendaRuheKandai42SuiZhongxingWangxinYanfaFuzerenOuJianxinBeiCituiHouZhuiwang/file.epub
ZhihuWendaRuheKandai42SuiZhongxingWangxinYanfaFuzerenOuJianxinBeiCituiHouZhuiwang/index.html
ZhihuWendaRuheKandai42SuiZhongxingWangxinYanfaFuzerenOuJianxinBeiCituiHouZhuiwang/css/__init__.py
ZhihuWendaRuheKandai42SuiZhongxingWangxinYanfaFuzerenOuJianxinBeiCituiHouZhuiwang/css/annotations.css
ZhihuWendaRuheKandai42SuiZhongxingWangxinYanfaFuzerenOuJianxinBeiCituiHouZhuiwang/css/main.css
ZhihuWendaRuheKandai42SuiZhongxingWangxinYanfaFuzerenOuJianxinBeiCituiHouZhuiwang/css/normalize.css
ZhihuWendaRuheKandai42SuiZhongxingWangxinYanfaFuzerenOuJianxinBeiCituiHouZhuiwang/css/popup.css
ZhihuWendaRuheKandai42SuiZhongxingWangxinYanfaFuzerenOuJianxinBeiCituiHouZhuiwang/font/__init__.py
ZhihuWendaRuheKandai42SuiZhongxingWangxinYanfaFuzerenOuJianxinBeiCituiHouZhuiwang/font/fontello.eot
ZhihuWendaRuheKandai42SuiZhongxingWangxinYanfaFuzerenOuJianxinBeiCituiHouZhuiwang/font/fontello.svg
ZhihuWendaRuheKandai42SuiZhongxingWangxinYanfaFuzerenOuJianxinBeiCituiHouZhuiwang/font/fontello.ttf
ZhihuWendaRuheKandai42SuiZhongxingWangxinYanfaFuzerenOuJianxinBeiCituiHouZhuiwang/font/fontello.woff
ZhihuWendaRuheKandai42SuiZhongxingWangxinYanfaFuzerenOuJianxinBeiCituiHouZhuiwang/img/__init__.py
ZhihuWendaRuheKandai42SuiZhongxingWangxinYanfaFuzerenOuJianxinBeiCituiHouZhuiwang/img/annotator-glyph-sprite.png
ZhihuWendaRuheKandai42SuiZhongxingWangxinYanfaFuzerenOuJianxinBeiCituiHouZhuiwang/img/annotator-icon-sprite.png
ZhihuWendaRuheKandai42SuiZhongxingWangxinYanfaFuzerenOuJianxinBeiCituiHouZhuiwang/img/apple-touch-icon.png
ZhihuWendaRuheKandai42SuiZhongxingWangxinYanfaFuzerenOuJianxinBeiCituiHouZhuiwang/img/cancelfullscreen.png
zhihu_wenda_ruhe_kandai_42_sui_zhongxing_wangxin_yanfa_fuzeren_ou_jianxin_bei_citui_hou_zhuiwang-2024.3.5.0.dist-info/METADATA
zhihu_wenda_ruhe_kandai_42_sui_zhongxing_wangxin_yanfa_fuzeren_ou_jianxin_bei_citui_hou_zhuiwang-2024.3.5.0.dist-info/WHEEL
zhihu_wenda_ruhe_kandai_42_sui_zhongxing_wangxin_yanfa_fuzeren_ou_jianxin_bei_citui_hou_zhuiwang-2024.3.5.0.dist-info/entry_points.txt
zhihu_wenda_ruhe_kandai_42_sui_zhongxing_wangxin_yanfa_fuzeren_ou_jianxin_bei_citui_hou_zhuiwang-2024.3.5.0.dist-info/top_level.txt
zhihu_wenda_ruhe_kandai_42_sui_zhongxing_wangxin_yanfa_fuzeren_ou_jianxin_bei_citui_hou_zhuiwang-2024.3.5.0.dist-info/RECORD
